LICENSE.txt
README.md
setup.cfg
setup.py
prometheus_aws_guardduty_exporter/__init__.py
prometheus_aws_guardduty_exporter/cli.py
prometheus_aws_guardduty_exporter/collector.py
prometheus_aws_guardduty_exporter.egg-info/PKG-INFO
prometheus_aws_guardduty_exporter.egg-info/SOURCES.txt
prometheus_aws_guardduty_exporter.egg-info/dependency_links.txt
prometheus_aws_guardduty_exporter.egg-info/entry_points.txt
prometheus_aws_guardduty_exporter.egg-info/requires.txt
prometheus_aws_guardduty_exporter.egg-info/top_level.txt
tests/test_collector.py
tests/test_linter.py