Metadata-Version: 2.1
Name: prometheus-aws-guardduty-exporter
Version: 2.0.0
Summary: Prometheus exporter for AWS GuardDuty
Home-page: https://github.com/spreaker/prometheus-aws-guardduty-exporter
Download-URL: https://github.com/spreaker/prometheus-aws-guardduty-exporter/archive/2.0.0.tar.gz
Author: Spreaker
Author-email: dev@spreaker.com
Keywords: prometheus,aws,guardduty
Requires-Python:  >= 3.11
Provides-Extra: dev
License-File: LICENSE.txt
